README.rst
setup.py
zulipbot/__init__.py
zulipbot/bot.py
zulipbot/zulip.py
zulipbot.egg-info/PKG-INFO
zulipbot.egg-info/SOURCES.txt
zulipbot.egg-info/dependency_links.txt
zulipbot.egg-info/requires.txt
zulipbot.egg-info/top_level.txt