Metadata-Version: 1.0
Name: zulipbot
Version: 0.0.1
Summary: The unofficial bot API for Zulip.
Home-page: http://github.com/stephsamson/zulipbot
Author: Steph Samson
Author-email: sdvsamson@gmail.com
License: MIT
Keywords: zulip bot api zulipbot
Platform: UNKNOWN
